fcw_service/__init__.py
fcw_service/collision_worker.py
fcw_service/interface.py
fcw_service/visualization.py
fcw_service-0.12.1.dist-info/METADATA
fcw_service-0.12.1.dist-info/WHEEL
fcw_service-0.12.1.dist-info/entry_points.txt
fcw_service-0.12.1.dist-info/RECORD
